{"id":"46467053","premium":false,"billing_type":{"id":"standard","name":"Стандарт"},"relations":[],"name":"Data Engineer","insider_interview":null,"response_letter_required":false,"area":{"id":"1","name":"Москва","url":"https://api.hh.ru/areas/1?host=hh.ru"},"salary":null,"type":{"id":"open","name":"Открытая"},"address":null,"allow_messages":true,"site":{"id":"hh","name":"hh.ru"},"experience":{"id":"between3And6","name":"От 3 до 6 лет"},"schedule":{"id":"fullDay","name":"Полный день"},"employment":{"id":"full","name":"Полная занятость"},"department":null,"contacts":null,"description":"<p><strong>Департамент информационных технологий города Москвы</strong> — команда профессионалов, чья работа, часто невидимая для невооруженного глаза, с каждым днём делает жизнь москвичей удобнее.</p> <p>В Продукт <strong>Управление данными</strong> ищем <strong>Data Engineer.</strong></p> <p>Сейчас команда активно растёт и продолжает набирать темп, поэтому мы в поисках новых талантов!</p> <p><strong>Что нужно будет делать:</strong></p> <ul> <li>Создание внутреннего фреймворка для унификации интеграции с разными источниками данных ( пока заложили фундамент, легаси не так много, можно и нужно будет предлагать свои варианты развития);</li> <li>Разработка пайплайнов загрузки данных из различных источников;</li> <li>Выбор и его обоснование технологического стека для перечисленных задач ( тут все еще очень подвижны ).</li> </ul> <p><strong>Что важно для нас:</strong></p> <ul> <li>Python</li> <li>Airflow, PySpark</li> <li>SQL - для быстрых проверок и рутинных задач</li> <li>Поверхностное понимание механизмов Gitlab CI / CD</li> <li>Интерес к Grafana и мониторингу в целом.</li> <li>Не будем просить развернуть бинарное дерево на доске, но поспрашиваем про твой опыт работы с nosql / sql базами данных ( тут целый зоопарк ).</li> </ul> <p><strong>Мы предлагаем:</strong></p> <ul> <li>Амбициозные проекты;</li> <li>Значимую роль в молодой команде экспертов, в которой коллеги всегда поддерживают друг друга;</li> <li>Открытую атмосферу, где ценят обратную связь, инициативность, креатив;</li> <li>Развивающие задачи и карьерные вызовы, реальные возможности для роста;</li> <li>Офис на ст. м Курская 5мин пешком.</li> </ul>","branded_description":null,"vacancy_constructor_template":null,"key_skills":[],"accept_handicapped":false,"accept_kids":false,"archived":false,"response_url":null,"specializations":[{"id":"1.221","name":"Программирование, Разработка","profarea_id":"1","profarea_name":"Информационные технологии, интернет, телеком"},{"id":"1.82","name":"Инженер","profarea_id":"1","profarea_name":"Информационные технологии, интернет, телеком"}],"professional_roles":[{"id":"96","name":"Программист, разработчик"}],"code":null,"hidden":false,"quick_responses_allowed":false,"driver_license_types":[],"accept_incomplete_resumes":false,"employer":{"id":"2427329","name":"ГКУ Инфогород","url":"https://api.hh.ru/employers/2427329?host=hh.ru","alternate_url":"https://hh.ru/employer/2427329","logo_urls":{"original":"https://hhcdn.ru/employer-logo-original/772017.png","90":"https://hhcdn.ru/employer-logo/3529025.png","240":"https://hhcdn.ru/employer-logo/3529026.png"},"vacancies_url":"https://api.hh.ru/vacancies?employer_id=2427329&host=hh.ru","trusted":true},"published_at":"2021-11-22T10:49:03+0300","created_at":"2021-11-22T10:49:03+0300","negotiations_url":null,"suitable_resumes_url":null,"apply_alternate_url":"https://hh.ru/applicant/vacancy_response?vacancyId=46467053","has_test":false,"test":null,"alternate_url":"https://hh.ru/vacancy/46467053","working_days":[],"working_time_intervals":[],"working_time_modes":[],"accept_temporary":false}