{"id":"49255493","premium":false,"billing_type":{"id":"standard_plus","name":"Стандарт плюс"},"relations":[],"name":"Data Engineer","insider_interview":null,"response_letter_required":false,"area":{"id":"1","name":"Москва","url":"https://api.hh.ru/areas/1?host=hh.ru"},"salary":{"from":3000,"to":null,"currency":"USD","gross":false},"type":{"id":"open","name":"Открытая"},"address":{"city":"Москва","street":"Краснопролетарская улица","building":"16с1","description":null,"lat":55.776978,"lng":37.60752,"raw":"Москва, Краснопролетарская улица, 16с1","metro":null,"metro_stations":[]},"allow_messages":true,"site":{"id":"hh","name":"hh.ru"},"experience":{"id":"between3And6","name":"От 3 до 6 лет"},"schedule":{"id":"remote","name":"Удаленная работа"},"employment":{"id":"full","name":"Полная занятость"},"department":null,"contacts":null,"description":"<p><strong>Кто мы? </strong></p> <p>Приложение App in the Air (AITA) — персональный ассистент полетов, который информирует пользователей о состоянии рейса, собирает статистику путешествий и помогает ориентироваться в аэропортах.</p> <p><strong>Thoth</strong> — родственная компания App in the Air, которая обрабатывает данные об индивидуальной истории полётов разными авиалиниями от 6 миллионов пользователей по всему миру и строит детализированные модели пассажиров. С их помощью мы рассчитываем динамику авиаперевозок и предлагаем крупнейшим авиалиниям и аэропортам стратегии оптимизации.</p> <p>Мы ищем <strong>Data Инженера</strong>, который автоматизирует пайплайны получения и обработки больших массивов данных.</p> <p><strong>Обязанности:</strong></p> <ul> <li>Проектирование DWH</li> <li>Автоматизация data- and ML- пайплайнов</li> <li>Масштабирование пайплайнов обработки данных и аналитических моделей</li> <li>Разработка архитектуры для автоматизации ML экспериментов и версионирования данных</li> <li>Автоматизация проверок качества данных</li> <li>Ревью кода коллег</li> </ul> <p> </p> <p><strong>Стек, инфраструктура, инструменты:</strong></p> <ul> <li>Python3.x</li> <li>PyCharm , Jupyter Notebooks</li> <li>Git, Atlassian (Jira, Confluence), Miro, Telegram</li> <li>GCP, AWS</li> </ul> <p> </p> <p><strong>Требования:</strong></p> <ul> <li>Знание <strong>Python</strong></li> <li>Умение писать качественный код</li> <li>Опыт проектирования <strong>DWH</strong></li> <li>Понимание преимуществ одного типа БД над другим в заданном контексте</li> <li>Опыт работы с реляционными базами данных (<strong>MySQL</strong>)</li> <li>Знание <strong>git, Github</strong></li> <li>Уверенная работа с unix-консолью</li> <li>Умение читать и писать документацию на английском</li> </ul> <p> </p> <p><strong>Плюсом будет:</strong></p> <ul> <li>Опыт работы с <strong>Google Cloud Platform (Datastore, Firebase, BigQuery…)</strong></li> <li>Опыт работы с <strong>Docker</strong></li> <li>Опыт работы с <strong>Kubernetes</strong></li> <li>Опыт работы с <strong>AWS</strong></li> <li>Опыт работы с<strong> RESTful API</strong></li> <li>Опыт работы с <strong>DVC</strong></li> <li>Опыт разработки аналитического дэшборда</li> <li>Опыт презентации своих результатов</li> </ul> <p><strong>Материальные блага:</strong></p> <ul> <li>Гибкий график, full-time удаленка</li> <li>Свой офис на Новослободской/Менделеевской (ещё два в Сиэттле и Вене)</li> <li>Кэшбэк на путешествия, забронированные через App in the Air</li> <li>Раз в полгода проводим All-Hands встречи российской и американской команд в разных частях света (Гонг-Конг, Тбилиси, Стамбул, Кипр - done).</li> <li>ДМС после испытательного срока</li> <li>Бесплатные обеды</li> <li>Оплата занятий английским</li> <li>Компенсация обучения/курсов</li> <li>Устройство по ТК РФ или по контракту в американскую компанию</li> </ul> <p><strong>Нематериальные блага:</strong></p> <ul> <li>Менторство от опытных наставников</li> <li>Прозрачная система развития и возможность карьерного роста</li> <li>Совместное участие в хакатонах (неоднократно побеждали в хакатонах в США и Европе + организуем внутри команды)</li> <li>Классный продукт: мы помогаем и объединяем frequent flyers по всему миру</li> <li>Свобода создавать и экспериментировать: мы не боимся пробовать новое и поддерживаем идеи</li> <li>Классная команда: мы помогаем друг другу расти, проводим лекции и воркшопы, учимся и учим</li> <li>Экспертиза: можно получить уникальные знания о тревел-индустрии</li> </ul>","branded_description":null,"vacancy_constructor_template":null,"key_skills":[{"name":"PostgreSQL"},{"name":"SQL"},{"name":"Python"},{"name":"ClickHouse"},{"name":"Big Data"},{"name":"ML"},{"name":"Hadoop"},{"name":"ETL"},{"name":"Elastic"},{"name":"RedShift"},{"name":"BigQuery"},{"name":"MySQL"}],"accept_handicapped":false,"accept_kids":false,"archived":false,"response_url":null,"specializations":[{"id":"1.82","name":"Инженер","profarea_id":"1","profarea_name":"Информационные технологии, интернет, телеком"},{"id":"1.420","name":"Администратор баз данных","profarea_id":"1","profarea_name":"Информационные технологии, интернет, телеком"},{"id":"1.25","name":"Аналитик","profarea_id":"1","profarea_name":"Информационные технологии, интернет, телеком"},{"id":"1.474","name":"Стартапы","profarea_id":"1","profarea_name":"Информационные технологии, интернет, телеком"}],"professional_roles":[{"id":"96","name":"Программист, разработчик"}],"code":null,"hidden":false,"quick_responses_allowed":false,"driver_license_types":[],"accept_incomplete_resumes":false,"employer":{"id":"3660004","name":"App in the Air","url":"https://api.hh.ru/employers/3660004?host=hh.ru","alternate_url":"https://hh.ru/employer/3660004","logo_urls":{"240":"https://hhcdn.ru/employer-logo/2847241.png","90":"https://hhcdn.ru/employer-logo/2847240.png","original":"https://hhcdn.ru/employer-logo-original/601521.png"},"vacancies_url":"https://api.hh.ru/vacancies?employer_id=3660004&host=hh.ru","trusted":true},"published_at":"2021-11-22T16:24:03+0300","created_at":"2021-11-22T16:24:03+0300","negotiations_url":null,"suitable_resumes_url":null,"apply_alternate_url":"https://hh.ru/applicant/vacancy_response?vacancyId=49255493","has_test":false,"test":null,"alternate_url":"https://hh.ru/vacancy/49255493","working_days":[],"working_time_intervals":[],"working_time_modes":[],"accept_temporary":false}