{"id":"49741363","premium":false,"billing_type":{"id":"standard","name":"Стандарт"},"relations":[],"name":"Senior Cost Engineer / Старший специалист по расчету затрат","insider_interview":null,"response_letter_required":false,"area":{"id":"1","name":"Москва","url":"https://api.hh.ru/areas/1?host=hh.ru"},"salary":null,"type":{"id":"open","name":"Открытая"},"address":null,"allow_messages":true,"site":{"id":"hh","name":"hh.ru"},"experience":{"id":"moreThan6","name":"Более 6 лет"},"schedule":{"id":"fullDay","name":"Полный день"},"employment":{"id":"full","name":"Полная занятость"},"department":null,"contacts":null,"description":"<p><strong>KAZ Minerals Russia </strong>is looking for potential candidates for the position of <strong>Senior Cost Engineer</strong> within <strong>Project Controls Department</strong> in our Moscow office (with subsequent rotation to Chukotka).</p> <p>Structural division: Project Controls Department</p> <p>Report to: Lead Cost Engineer</p> <p><strong>R<strong>ES</strong>PONSIBILITIES:</strong></p> <ul> <li>Assist Lead Cost Engineer to provide timely, accurate and relevant cost data for monthly and regular cost reporting;</li> <li>Advise the Senior Cost Engineer and Project team of results of cost data analysis;</li> <li>Responsible for coding of items in contracts and Purchase Orders to ensure correct budget allocation;</li> <li>Maintain and control of the project budget;</li> <li>Liaise with all managers to ascertain costs and schedule impact of trends and changes;</li> <li>Supervision of trend and scope change program;</li> <li>Monitor and maintain the EPCM and management forecasts (if applicable);</li> <li>Supervise regular cost reviews and prepare data for inclusion in the Definitive Estimate;</li> <li>Prepare detailed commitment and cash flows;</li> <li>Maintain PRISM Cost Module system data including the transfer of cost and information from the PRISM Contracts, Procurement and Invoices modules.</li> </ul> <p><strong>REQUIREMENTS:</strong></p> <ul> <li>Bachelor Degree in Finance, Engineering, or Construction Management preferred;</li> <li>7+ years of Project Cost Engineering experience;</li> <li>Experience in all phases of project implementation from feasibility study to commissioning and start-up;</li> <li>Proven capability to undertake all aspects of cost control;</li> <li>Proficient with project controls specialist software and generic database &amp; spreadsheet software – PRISM preferred;</li> <li>Advanced MS Excel user;</li> <li>Languages: English is essential, Russian Fluent.</li> </ul> <p><strong>CONDITIONS:</strong></p> <ul> <li> <p>Direct contract with KAZ Minerals Russia LLC;</p> </li> <li> <p>Work schedule: Monday-Friday: from 9 am till 6 pm</p> </li> <li>Competitive salary and benefits;</li> <li>Medical insurance;</li> <li>Corporate lunches;</li> <li>Location: Moscow City</li> <li><strong>Rotation to Chukotka - Q3 2022</strong></li> </ul>","branded_description":null,"vacancy_constructor_template":null,"key_skills":[{"name":"Английский язык"},{"name":"Project management"},{"name":"PRISM"},{"name":"Расчет затрат"},{"name":"Cost Analysis"},{"name":"Construction"}],"accept_handicapped":false,"accept_kids":false,"archived":false,"response_url":null,"specializations":[{"id":"2.44","name":"Бюджетирование и планирование","profarea_id":"2","profarea_name":"Бухгалтерия, управленческий учет, финансы предприятия"},{"id":"2.342","name":"Финансовый анализ","profarea_id":"2","profarea_name":"Бухгалтерия, управленческий учет, финансы предприятия"},{"id":"2.343","name":"Финансовый контроль","profarea_id":"2","profarea_name":"Бухгалтерия, управленческий учет, финансы предприятия"},{"id":"2.344","name":"Финансовый менеджмент","profarea_id":"2","profarea_name":"Бухгалтерия, управленческий учет, финансы предприятия"},{"id":"2.425","name":"Экономист","profarea_id":"2","profarea_name":"Бухгалтерия, управленческий учет, финансы предприятия"}],"professional_roles":[{"id":"137","name":"Финансовый менеджер"}],"code":null,"hidden":false,"quick_responses_allowed":false,"driver_license_types":[],"accept_incomplete_resumes":false,"employer":{"id":"4256239","name":"KAZ Minerals Russia LLC","url":"https://api.hh.ru/employers/4256239?host=hh.ru","alternate_url":"https://hh.ru/employer/4256239","logo_urls":{"90":"https://hhcdn.ru/employer-logo/3398205.png","240":"https://hhcdn.ru/employer-logo/3398206.png","original":"https://hhcdn.ru/employer-logo-original/739307.png"},"vacancies_url":"https://api.hh.ru/vacancies?employer_id=4256239&host=hh.ru","trusted":true},"published_at":"2021-11-18T10:15:59+0300","created_at":"2021-11-18T10:15:59+0300","negotiations_url":null,"suitable_resumes_url":null,"apply_alternate_url":"https://hh.ru/applicant/vacancy_response?vacancyId=49741363","has_test":false,"test":null,"alternate_url":"https://hh.ru/vacancy/49741363","working_days":[],"working_time_intervals":[],"working_time_modes":[],"accept_temporary":false}