{"id":"49834025","premium":false,"billing_type":{"id":"standard_plus","name":"Стандарт плюс"},"relations":[],"name":"Scrum Master (Remote)","insider_interview":null,"response_letter_required":false,"area":{"id":"1","name":"Москва","url":"https://api.hh.ru/areas/1?host=hh.ru"},"salary":null,"type":{"id":"open","name":"Открытая"},"address":null,"allow_messages":true,"site":{"id":"hh","name":"hh.ru"},"experience":{"id":"between3And6","name":"От 3 до 6 лет"},"schedule":{"id":"fullDay","name":"Полный день"},"employment":{"id":"full","name":"Полная занятость"},"department":null,"contacts":null,"description":"<p>We are looking for a talented Scrum Master to join our Release Engineering group.</p> <p>Our company is Cloud Linux Inc. - the maker of the #1 OS for web-hosting providers. We develop our products -- CloudLinux OS, KernelCare, Imunify360, and Imunify Email -- using the most innovative technologies. Our products are used by thousands of companies around the world, including Dell, GoDaddy, IBM, Zoom, and many others</p> <p>Work is fully remote, with flexible hours, where you can plan your day and work from anywhere in the world.</p> <p>More details about the project you can find on the product website KernelCare.com, about the company on Cloudlinux.com.</p> <p>Join us to make a difference!</p> <p>What you will do:</p> <ul> <li>Facilitate the work of the team or group of teams.</li> <li>Gatekeeper for the Scrum Framework, facilitating Scrum events as needed.</li> <li>Acts as the Agile coach for the Agile team, educating it in Agile practices.</li> <li>Keep agile-related instrumentum (mostly Confluence) in total order.</li> <li>Provides guidance to assist the teams in constantly improving the quality of their deliverables and meeting the Definition of Done (DoD).</li> <li>Work constantly to make sure that goals, scope, product domain, company agenda are distributed equally among all stakeholders.</li> <li>Remove impediments in the team.</li> <li>Manages team level execution risks.</li> <li>Support team members with coaching in self-organization and cross-functionality.</li> <li>Facilitate continuous improvements via retrospectives and demo sessions.</li> </ul> <p> </p> <p>Qualifications that we are looking for:</p> <ul> <li>Relevant 4+ years’ experience.</li> <li>Fluent Agile/Scrum methodologies and tools usage (JIRA, confluence, etc.).</li> <li>Strong quality and continuous improvement mindset.</li> <li>Excellent facilitation, coordination, and communication skills.</li> <li>Good technical English.</li> <li>Good technical background, understanding of SW development process life-cycle.</li> <li>Self-motivated, self-learning, and readiness for new challenges.</li> </ul> <p> </p> <p>What’s in it for you?</p> <ul> <li>A great opportunity for professional development within the young and fast-growing company.</li> <li>Interesting and challenging projects.</li> <li>Knowledge-Exchange.</li> <li>Remote work with long-term employment on a full-time basis under contract.</li> <li>High-level compensation based on the performance reviews.</li> <li>Compensation in the US dollars.</li> <li>Flexible working hours.</li> <li>Paid one month vacation per year and sick leaves.</li> <li>Medical insurance (according to the company policy).</li> <li>Days off on national holidays.</li> <li>English educational programs (Lingua-Leo online course &amp; Speaking Club).</li> <li>Individual coach sessions.</li> <li>Ability to study and attend seminars and training according to the request.</li> <li>Co-working and gym/sports compensations (according to the company policy).</li> <li>The opportunity to receive a reward for the most innovative idea that the company can patent.</li> </ul> <p> </p> <p>What are you waiting for?</p> <p>Talk to us and make this a win-win for you and us. We are CloudLinux, and we need you to make the next move. Apply now!</p> <p> </p> <p><em>By applying for this position, you agree with </em><em>Cloudlinux Privacy Policy</em><em> and give us your consent to maintain and process your personal data with this respect. Please read our Privacy Policy for more information.</em></p>","branded_description":null,"vacancy_constructor_template":null,"key_skills":[{"name":"Agile Project Management"},{"name":"Английский язык"},{"name":"Atlassian Jira"},{"name":"Scrum"},{"name":"Atlassian Confluence"}],"accept_handicapped":false,"accept_kids":false,"archived":false,"response_url":null,"specializations":[{"id":"1.221","name":"Программирование, Разработка","profarea_id":"1","profarea_name":"Информационные технологии, интернет, телеком"},{"id":"1.82","name":"Инженер","profarea_id":"1","profarea_name":"Информационные технологии, интернет, телеком"}],"professional_roles":[{"id":"107","name":"Руководитель проектов"}],"code":null,"hidden":false,"quick_responses_allowed":false,"driver_license_types":[],"accept_incomplete_resumes":false,"employer":{"id":"1245452","name":"Cloud Linux","url":"https://api.hh.ru/employers/1245452?host=hh.ru","alternate_url":"https://hh.ru/employer/1245452","logo_urls":{"240":"https://hhcdn.ru/employer-logo/1614523.png","90":"https://hhcdn.ru/employer-logo/1614522.png","original":"https://hhcdn.ru/employer-logo-original/293033.png"},"vacancies_url":"https://api.hh.ru/vacancies?employer_id=1245452&host=hh.ru","trusted":true},"published_at":"2021-11-22T13:09:43+0300","created_at":"2021-11-22T13:09:43+0300","negotiations_url":null,"suitable_resumes_url":null,"apply_alternate_url":"https://hh.ru/applicant/vacancy_response?vacancyId=49834025","has_test":true,"test":{"required":true},"alternate_url":"https://hh.ru/vacancy/49834025","working_days":[],"working_time_intervals":[],"working_time_modes":[],"accept_temporary":false}